README.rst
setup.cfg
setup.py
firepit/__init__.py
firepit/exception.py
firepit/messaging.py
python_firepit.egg-info/PKG-INFO
python_firepit.egg-info/SOURCES.txt
python_firepit.egg-info/dependency_links.txt
python_firepit.egg-info/requires.txt
python_firepit.egg-info/top_level.txt