Metadata-Version: 1.1
Name: python-firepit
Version: 0.0.6
Summary: A Python Google firebase framework to handle REST-calls.
Home-page: https://github.com/twe82/python-firepit
Author: Thomas Wehner
Author-email: thomas.wehner@tro-lan.de
License: MIT
Keywords: firebase,messaging,android
Platform: UNKNOWN
Classifier: Development Status :: 1 - Planning
Classifier: Intended Audience :: Developers
Classifier: License :: OSI Approved :: MIT License
Classifier: Topic :: System :: Distributed Computing
Classifier: Programming Language :: Python
Classifier: Programming Language :: Python :: 3
Classifier: Programming Language :: Python :: 3.5
Classifier: Operating System :: OS Independent
